point_pypi_demo/__init__.py
point_pypi_demo/helloworld.py
point_pypi_demo-0.0.1.dist-info/LICENSE
point_pypi_demo-0.0.1.dist-info/METADATA
point_pypi_demo-0.0.1.dist-info/WHEEL
point_pypi_demo-0.0.1.dist-info/entry_points.txt
point_pypi_demo-0.0.1.dist-info/top_level.txt
point_pypi_demo-0.0.1.dist-info/RECORD
