Metadata-Version: 2.1
Name: point-pypi-demo
Version: 0.0.1
Summary: point world
Home-page: https://github.com/pointworld/point_pypi_demo
Author: Point
License: UNKNOWN
Platform: UNKNOWN
Classifier: Programming Language :: Python :: 3
Classifier: License :: OSI Approved :: MIT License
Classifier: Operating System :: OS Independent
Requires-Dist: numpy (==1.14.4)
